dof/__init__.py
dof/cli.py
dof/dof.py
dof/main.py
dof/actions/__init__.py
dof/actions/manipulation.py
dof/actions/movement.py
dof/actions/robot.py
dof/cookbook/chain.ipynb
dof/core/__init__.py
dof/core/base.py
dof/core/chain.py
dof/core/exceptions.py
dof/executors/__init__.py
dof/executors/base_robot.py
dof/executors/isaac_sim.py
dof/executors/simulator.py
dof/llm/__init__.py
dof/llm/llm_service.py
dof_ai-1.8.3.dist-info/licenses/LICENSE
dof_ai-1.8.3.dist-info/METADATA
dof_ai-1.8.3.dist-info/WHEEL
dof_ai-1.8.3.dist-info/entry_points.txt
dof_ai-1.8.3.dist-info/top_level.txt
dof_ai-1.8.3.dist-info/RECORD
