Metadata-Version: 2.4
Name: dof-ai
Version: 1.8.3
Summary: dof is your LangChain for robotics
Author-email: Pieter Becking <ph.becking@gmail.com>
Maintainer-email: Pieter Becking <ph.becking@gmail.com>
License: MIT license
Project-URL: bugs, https://github.com/pieterbecking/dof/issues
Project-URL: changelog, https://github.com/pieterbecking/dof/blob/master/changelog.md
Project-URL: homepage, https://github.com/pieterbecking/dof
Classifier: Development Status :: 4 - Beta
Classifier: Intended Audience :: Developers
Classifier: License :: OSI Approved :: MIT License
Classifier: Natural Language :: English
Classifier: Programming Language :: Python :: 3
Classifier: Programming Language :: Python :: 3.8
Classifier: Programming Language :: Python :: 3.9
Classifier: Programming Language :: Python :: 3.10
Classifier: Programming Language :: Python :: 3.11
License-File: LICENSE
Requires-Dist: typer>=0.9.0
Requires-Dist: rich>=13.0.0
Requires-Dist: openai>=1.0.0
Requires-Dist: python-dotenv>=1.0.0
Provides-Extra: dev
Requires-Dist: coverage; extra == "dev"
Requires-Dist: mypy; extra == "dev"
Requires-Dist: pytest; extra == "dev"
Requires-Dist: ruff; extra == "dev"
Dynamic: license-file
